git_stats_report/__init__.py
git_stats_report/__main__.py
git_stats_report/entrypoint.py
git_stats_report/git_stats.py
git_stats_report/logger.py
git_stats_report/py.typed
git_stats_report/utils.py
git_stats_report/strategy/__init__.py
git_stats_report/strategy/from_date.py
git_stats_report/strategy/from_latest_tag.py
git_stats_report/strategy/strategy.py
git_stats_report-0.3.2.dist-info/LICENSE
git_stats_report-0.3.2.dist-info/METADATA
git_stats_report-0.3.2.dist-info/WHEEL
git_stats_report-0.3.2.dist-info/entry_points.txt
git_stats_report-0.3.2.dist-info/top_level.txt
git_stats_report-0.3.2.dist-info/RECORD
