Metadata-Version: 2.1
Name: git-stats-report
Version: 0.3.2
Author-email: Juan José Farina <juanjosefarina.jjf@gmail.com>, "Ezequiel L. Castaño" <castanoezequielleonardo@gmail.com>
License: MIT
Project-URL: homepage, https://github.com/JuanJFarina/git-stats-report
Project-URL: documentation, https://github.com/JuanJFarina/git-stats-report
Project-URL: repository, https://github.com/JuanJFarina/git-stats-report
Project-URL: changelog, https://github.com/JuanJFarina/git-stats-report/blob/master/CHANGELOG.md
Classifier: Development Status :: 4 - Beta
Classifier: Programming Language :: Python
Classifier: License :: OSI Approved :: MIT License
Classifier: Intended Audience :: Developers
Classifier: Framework :: Pytest
Classifier: Environment :: Console
Classifier: Natural Language :: English
Classifier: Operating System :: OS Independent
Classifier: Topic :: Software Development :: Version Control :: Git
Classifier: Typing :: Typed
Requires-Python: >=3.8
License-File: LICENSE
Requires-Dist: typer ==0.9.0
Requires-Dist: typing-extensions ==4.10.0
